webpagetracker/__init__.py
webpagetracker-1.0.dist-info/DESCRIPTION.rst
webpagetracker-1.0.dist-info/METADATA
webpagetracker-1.0.dist-info/RECORD
webpagetracker-1.0.dist-info/WHEEL
webpagetracker-1.0.dist-info/metadata.json
webpagetracker-1.0.dist-info/top_level.txt
webtracker/__init__.py
