Metadata-Version: 2.0
Name: webpagetracker
Version: 1.0
Summary: Track web pages and inform changes through email
Home-page: http://github.com/cjlcarvalho/webpagetracker
Author: Caio Jordão Carvalho
Author-email: caiojcarvalho@gmail.com
License: LGPL
Keywords: webpagetracker webtracker tracker web scraper
Platform: UNKNOWN
Requires-Python: >=3
Requires-Dist: requests
